ejerico/__init__.py
ejerico/bootstrap.py
ejerico/harvester.py
ejerico/harvester_config.py
ejerico/harvester_data.py
ejerico/harvester_database.py
ejerico/harvester_helper.py
ejerico/json
ejerico/main.py
ejerico/python
ejerico/query_test.py
ejerico/xml
ejerico/__pycache__/bootstrap.cpython-37.pyc
ejerico/__pycache__/harvester.cpython-37.pyc
ejerico/__pycache__/harvester_config.cpython-37.pyc
ejerico/__pycache__/harvester_data.cpython-37.pyc
ejerico/__pycache__/harvester_database.cpython-37.pyc
ejerico/__pycache__/harvester_helper.cpython-37.pyc
ejerico_harvester-0.0.1.dist-info/DESCRIPTION.rst
ejerico_harvester-0.0.1.dist-info/METADATA
ejerico_harvester-0.0.1.dist-info/RECORD
ejerico_harvester-0.0.1.dist-info/WHEEL
ejerico_harvester-0.0.1.dist-info/entry_points.txt
ejerico_harvester-0.0.1.dist-info/metadata.json
ejerico_harvester-0.0.1.dist-info/top_level.txt
