Metadata-Version: 2.0
Name: ejerico-harvester
Version: 0.0.1
Summary: Package supporting configuration and orchestration processes of provider harvesters
Home-page: UNKNOWN
Author: maav
Author-email: maalcalde@socib.es
License: EJERICO - SOFTWARE LICENSE
Platform: UNKNOWN
Classifier: Development Status :: 2 - Pre-Alpha
Classifier: Programming Language :: Python
Classifier: Programming Language :: Python :: 3.3
Classifier: Programming Language :: Python :: 3.4
Classifier: Programming Language :: Python :: 3.5
Classifier: Programming Language :: Python :: 3.6
Classifier: Programming Language :: Python :: 3.7
Classifier: Programming Language :: Python :: 3.8
Classifier: Topic :: Software Development :: Libraries :: Python Modules
Classifier: Operating System :: OS Independent
Classifier: Natural Language :: English
Requires-Dist: atoma
Requires-Dist: ejerico-sdk
Requires-Dist: geopy
Requires-Dist: netCDF4
Requires-Dist: numpy
Requires-Dist: sqlite3-api
